{
  "Stores": [

    {
      "name": "Archivio2017",
      "description": "Archivio 2017",
      "storeTypeName": "Delineat.Workflow.Core.Stores.DWFileFolderStore, Delineat.Workflow.Core.Stores",
      "settings": [
        {
          "key": "rootDirectoryPath",
          "value": "C:\\Delineat\\DATI\\ARCHIVIO_2017"
        }
      ]
    },
    {
      "name": "Archivio2016",
      "description": "Archivio 2016",
      "storeTypeName": "Delineat.Workflow.Core.Stores.DWFileFolderStore, Delineat.Workflow.Core.Stores",
      "settings": [
        {
          "key": "rootDirectoryPath",
          "value": "C:\\Delineat\\DATI\\ARCHIVIO_2016"
        }
      ]
    },
    {
      "name": "Archivio2015",
      "description": "Archivio 2015",
      "storeTypeName": "Delineat.Workflow.Core.Stores.DWFileFolderStore, Delineat.Workflow.Core.Stores",
      "settings": [
        {
          "key": "rootDirectoryPath",
          "value": "C:\\Delineat\\DATI\\ARCHIVIO_2015"
        }
      ]
    }

  ]
}